[
  {
    "SequenceNumber":10,
    "Name": ".NET",
    "Slug": "dotnet",
    "Cover": "cats/cat_dotnet.jpg",
    "Children": [
      {
        "SequenceNumber":1001,
        "Name": "Web API",
        "Slug": "dotnet-web-api",
        "Cover": "cats/cat_dotnetwebapi.jpg"
      },
      {
        "SequenceNumber":1002,
        "Name": "Razor Pages",
        "Slug": "dotnet-web-razor-pages",
        "Cover": "cats/cat_razorpages.jpeg"
      },
      {
        "SequenceNumber":1003,
        "Name": "MVC",
        "Slug": "dotnet-web-mvc",
        "Cover": "cats/cat_aspnetcoremvc.jpg"
      },
      {
        "SequenceNumber":1004,
        "Name": "Blazor",
        "Slug": "dotnet-web-blazor",
        "Cover": "cats/cat_blazor.jpg"
      },
      {
        "SequenceNumber":1005,
        "Name": "MAUI",
        "Slug": "dotnet-mobile-maui",
        "Cover": "cats/cat_maui.png"
      },
      {
        "SequenceNumber":1006,
        "Name": "Xamarin",
        "Slug": "dotnet-mobile-xamarin",
        "Cover": "cats/cat_xamarin.jpg"
      },
      {
        "SequenceNumber":1007,
        "Name": "WPF",
        "Slug": "dotnet-desktop-wpf",
        "Cover": "cats/cat_wpf.gif"
      },
      {
        "SequenceNumber":1008,
        "Name": "Winform",
        "Slug": "dotnet-desktop-winform",
        "Cover": "cats/cat_winform.png"
      },
      {
        "SequenceNumber":1009,
        "Name": "WinUI",
        "Slug": "dotnet-desktop-winui",
        "Cover": "cats/cat_winui.jfif"
      },
      {
        "SequenceNumber":1010,
        "Name": "UWP",
        "Slug": "dotnet-desktop-uwp",
        "Cover": "cats/cat_uwp.png"
      },
      {
        "SequenceNumber":1011,
        "Name": "EF Core",
        "Slug": "dotnet-ef-core",
        "Cover": "cats/cat_console.gif"
      },
      {
        "SequenceNumber":1012,
        "Name": "Dapper",
        "Slug": "dotnet-orm-dapper",
        "Cover": "cats/cat_dapper.png"
      },
      {
        "SequenceNumber":1013,
        "Name": "OpenXML",
        "Slug": "dotnet-openxml",
        "Cover": "cats/cat_openxml.jfif"
      },
      {
        "SequenceNumber":1014,
        "Name": ".NET相关",
        "Slug": "dotnet-more-dotnet-other",
        "Cover": "cats/cat_dotnetabout.png"
      }
    ]
  },
  {
    "SequenceNumber":20,
    "Name": "大前端",
    "Slug": "Large-front-end",
    "Cover": "cats/category.jpg",
    "Children": [
      {
        "SequenceNumber":2001,
        "Name": "Flutter",
        "Slug": "Large-front-end-flutter",
        "Cover": "cats/cat_flutter.jpeg"
      },
      {
        "SequenceNumber":2002,
        "Name": "React",
        "Slug": "Large-front-end-react",
        "Cover": "cats/cat_react.jpeg"
      },
      {
        "SequenceNumber":2003,
        "Name": "Vue",
        "Slug": "Large-front-end-vue",
        "Cover": "cats/cat_vue.jpeg"
      },
      {
        "SequenceNumber":2004,
        "Name": "TypeScript",
        "Slug": "Large-front-end-TypeScript",
        "Cover": "cats/cat_typescript.jpeg"
      },
      {
        "SequenceNumber":2005,
        "Name": "HTML",
        "Slug": "Large-front-end-html",
        "Cover": "cats/cat_html.jpeg"
      },
      {
        "SequenceNumber":2006,
        "Name": "CSS",
        "Slug": "Large-front-end-html",
        "Cover": "cats/cat_html.jpeg"
      },
      {
        "SequenceNumber":2007,
        "Name": "Bootstrap",
        "Slug": "Large-front-end-Bootstrap",
        "Cover": "cats/cat_bootstrap.jpeg"
      },
      {
        "SequenceNumber":2008,
        "Name": "SwiftUI",
        "Slug": "Large-front-end-swiftui",
        "Cover": "cats/cat_swiftui.jpeg"
      },
      {
        "SequenceNumber":2009,
        "Name": "Qt",
        "Slug": "more-language-qt",
        "Cover": "cats/cat_qt.png"
      },
      {
        "SequenceNumber":2010,
        "Name": "更多前端",
        "Slug": "Large-front-end-more",
        "Cover": "cats/cat_typescript.jpeg"
      }
    ]
  },
  {
    "SequenceNumber":30,
    "Name": "数据库",
    "Slug": "database",
    "Cover": "cats/category.jpg",
    "Children": [
      {
        "SequenceNumber":3001,
        "Name": "MySQL",
        "Slug": "database-mysql",
        "Cover": "cats/cat_mysql.jpeg"
      },
      {
        "SequenceNumber":3002,
        "Name": "Sqlite",
        "Slug": "database-sqlite",
        "Cover": "cats/cat_sqlite.jpeg"
      },
      {
        "SequenceNumber":3003,
        "Name": "数据库相关",
        "Slug": "database-about",
        "Cover": "cats/cat_mysql.jpeg"
      }
    ]
  },
  {
    "SequenceNumber":40,
    "Name": "更多语言",
    "Slug": "more-language",
    "Cover": "cats/category.jpg",
    "Children": [
      {
        "SequenceNumber":4001,
        "Name": "Go",
        "Slug": "more-language-go",
        "Cover": "cats/cat_go.jpeg"
      },
      {
        "SequenceNumber":4002,
        "Name": "Java",
        "Slug": "more-language-java",
        "Cover": "cats/cat_java.jpeg"
      },
      {
        "SequenceNumber":4003,
        "Name": "C++",
        "Slug": "more-language-cpp",
        "Cover": "cats/cat_cpp.jpeg"
      }
    ]
  },
  {
    "SequenceNumber":50,
    "Name": "课程分享",
    "Slug": "course",
    "Cover": "cats/category.jpg",
    "Children": [
      {
        "SequenceNumber":5001,
        "Name": ".NET课程",
        "Slug": "course-dotnet-course",
        "Cover": "cats/cat_dotnet_course.png"
      }
    ]
  },
  {
    "SequenceNumber":60,
    "Name": "更多分享",
    "Slug": "other",
    "Cover": "cats/category.jpg",
    "Children": [
      {
        "SequenceNumber":6001,
        "Name": "Redis",
        "Slug": "redis",
        "Cover": "cats/cat_redis.jpeg"
      },
      {
        "SequenceNumber":6002,
        "Name": "RabbitMQ",
        "Slug": "RabbitMQ",
        "Cover": "cats/cat_RabbitMQ.jpeg"
      },
      {
        "SequenceNumber":6003,
        "Name": "Linux",
        "Slug": "linux",
        "Cover": "cats/cat_linux.jpeg"
      },
      {
        "SequenceNumber":6004,
        "Name": "Docker",
        "Slug": "docker",
        "Cover": "cats/cat_docker.jpeg"
      },
      {
        "SequenceNumber":6005,
        "Name": "IDE",
        "Slug": "other-share-ide",
        "Cover": "cats/cat_ide.jpeg"
      },
      {
        "SequenceNumber":6006,
        "Name": "软件分享",
        "Slug": "other-share-software",
        "Cover": "cats/cat_software.jpeg"
      },
      {
        "SequenceNumber":6007,
        "Name": "架构设计",
        "Slug": "other-architecture-design",
        "Cover": "cats/cat_architecturedesign.jpeg"
      },
      {
        "SequenceNumber":6008,
        "Name": "职场生活",
        "Slug": "other-workplace-statement",
        "Cover": "cats/cat_workplace_statement.jpeg"
      },
      {
        "SequenceNumber":6009,
        "Name": "开源项目",
        "Slug": "other-Open-source-project",
        "Cover": "cats/cat_opensource.jpeg"
      },
      {
        "SequenceNumber":6010,
        "Name": "单元测试",
        "Slug": "other-unit-test",
        "Cover": "cats/cat_unittest.jpeg"
      },
      {
        "SequenceNumber":6011,
        "Name": "技巧分享",
        "Slug": "other-Skill-sharing",
        "Cover": "cats/cat_Skill.jpeg"
      },
      {
        "SequenceNumber":6012,
        "Name": "科技生活",
        "Slug": "other-science-and-technology-life",
        "Cover": "cats/cat_science.jpeg"
      },
      {
        "SequenceNumber":6013,
        "Name": "硬件相关",
        "Slug": "other-hardware",
        "Cover": "cats/cat_hardware.jpg"
      }
    ]
  }
]